promtext_cli/__init__.py
promtext_cli/main.py
promtext_cli-0.1.1.dist-info/METADATA
promtext_cli-0.1.1.dist-info/WHEEL
promtext_cli-0.1.1.dist-info/entry_points.txt
promtext_cli-0.1.1.dist-info/RECORD
