Metadata-Version: 2.3
Name: promtext-cli
Version: 0.1.1
Summary: Prometheus Textfile Tooling
Project-URL: Issues, https://github.com/margau/promtext-cli/issues
Project-URL: Source, https://github.com/margau/promtext-cli
Author-email: margau <dev@marvingaube.de>
License-Expression: GPL-3.0
Keywords: Prometheus
Requires-Python: >=3.7
Requires-Dist: prometheus-client
